MANIFEST.in
ez_setup.py
setup.py
SAPO_Broker.egg-info/PKG-INFO
SAPO_Broker.egg-info/SOURCES.txt
SAPO_Broker.egg-info/dependency_links.txt
SAPO_Broker.egg-info/requires.txt
SAPO_Broker.egg-info/top_level.txt
src/Broker/Messages.py
src/Broker/__init__.py
src/Broker/Clients/Async.py
src/Broker/Clients/Minimal.py
src/Broker/Clients/__init__.py
src/Broker/Codecs/Protobuf.py
src/Broker/Codecs/Thrift.py
src/Broker/Codecs/__init__.py
src/Broker/Codecs/autogen/__init__.py
src/Broker/Codecs/autogen/protobuf_2/__init__.py
src/Broker/Codecs/autogen/protobuf_2/broker_pb2.py
src/Broker/Codecs/autogen/thrift/__init__.py
src/Broker/Codecs/autogen/thrift/broker/__init__.py
src/Broker/Codecs/autogen/thrift/broker/constants.py
src/Broker/Codecs/autogen/thrift/broker/ttypes.py
src/Broker/Transport/Base.py
src/Broker/Transport/DropBox.py
src/Broker/Transport/HTTP.py
src/Broker/Transport/INET.py
src/Broker/Transport/SSL.py
src/Broker/Transport/TCP.py
src/Broker/Transport/UDP.py
src/Broker/Transport/__init__.py