Metadata-Version: 1.0
Name: SAPO-Broker
Version: 0.0.2
Summary: SAPO Broker python client
Home-page: http://oss.sapo.pt/#!broker
Author: Cláudio Valente
Author-email: broker@softwarelivre.sapo.pt
License: UNKNOWN
Platform: UNKNOWN
Classifier: Development Status :: 3 - Alpha
Classifier: Intended Audience :: Developers
Classifier: Operating System :: OS Independent
Classifier: Programming Language :: Python :: 2.5
Classifier: Programming Language :: Python :: 2.6
Classifier: Programming Language :: Python :: 2.7
Classifier: Topic :: Software Development :: Libraries :: Python Modules
